pdf_page_annotator/PDFAnnotator.py
pdf_page_annotator/__init__.py
pdf_page_annotator/preprocess.py
pdf_page_annotator/prompts.py
pdf_page_annotator-0.3.0.dist-info/LICENSE
pdf_page_annotator-0.3.0.dist-info/METADATA
pdf_page_annotator-0.3.0.dist-info/WHEEL
pdf_page_annotator-0.3.0.dist-info/top_level.txt
pdf_page_annotator-0.3.0.dist-info/RECORD
