Metadata-Version: 2.1
Name: pdf_page_annotator
Version: 0.3.0
Summary: A light weight library to extract the table of contents and tag them to the pages containing the content.
Home-page: https://github.com/ChinmayShrivastava/pdf-page-annotator
Author: Chinmay Shrivastava
Author-email: cshrivastava99@gmail.com
License: GPLv3
Classifier: Development Status :: 3 - Alpha
Classifier: Intended Audience :: Developers
Classifier: License :: OSI Approved :: GNU General Public License v3 (GPLv3)
Classifier: Programming Language :: Python :: 3
Classifier: Environment :: MacOS X
Classifier: Environment :: Win32 (MS Windows)
Classifier: Environment :: X11 Applications
License-File: LICENSE
Requires-Dist: llama-index
Requires-Dist: pypdf
Requires-Dist: python-dotenv
